{
  "id": "tokyo_kokubunji_west_tokyo",
  "name": "WEST TOKYO (旧結有)",
  "prefecture": "東京都",
  "city": "国分寺市",
  "address": "東京都小金井市・国分寺市エリア",
  "image": "/images/shops/no_image.jpg",
  "rating": 0,
  "reviewCount": 0,
  "price": "60分 12,000円～",
  "hours": "12:00～翌5:00",
  "isPremium": false,
  "tags": [
    "完全個室",
    "深夜営業"
  ],
  "websiteUrl": "https://esthe-westtokyo.com/",
  "nearestStation": "武蔵小金井駅 / 国分寺駅",
  "description": "武蔵小金井・国分寺のメンズエステ。旧店名「結有」。料金システム: 60分12,000円 / 90分16,000円 / 120分20,000円",
  "brandId": "west_tokyo",
  "therapists": [
    "west_tokyo_1",
    "west_tokyo_2",
    "west_tokyo_3",
    "west_tokyo_4",
    "west_tokyo_5",
    "west_tokyo_6",
    "west_tokyo_7",
    "west_tokyo_8",
    "west_tokyo_9",
    "west_tokyo_10",
    "west_tokyo_11",
    "west_tokyo_12",
    "west_tokyo_13",
    "west_tokyo_14",
    "west_tokyo_15",
    "west_tokyo_16",
    "west_tokyo_17",
    "west_tokyo_18",
    "west_tokyo_19",
    "west_tokyo_20",
    "west_tokyo_21",
    "west_tokyo_22",
    "west_tokyo_23",
    "west_tokyo_24",
    "west_tokyo_25",
    "west_tokyo_26",
    "west_tokyo_27",
    "west_tokyo_28",
    "west_tokyo_29",
    "west_tokyo_30"
  ]
}