{
  "id": 1071,
  "name": "アロマワン",
  "prefecture": "大阪府",
  "city": "日本橋",
  "area": "日本橋",
  "address": "大阪市中央区日本橋エリア",
  "image": "/images/shops/no_image.jpg",
  "rating": 0,
  "reviewCount": 0,
  "price": "60分 9,000円～",
  "hours": "12:00～翌5:00",
  "isPremium": false,
  "tags": [
    "カード支払いOK"
  ],
  "websiteUrl": "https://aromaoneosaka.com/top",
  "nearestStation": "日本橋駅",
  "description": "大阪日本橋のメンズエステ。 / 料金システム: 60分9,000円 / 90分12,000円 / 120分15,000円",
  "therapists": [
    {
      "id": "1071-1",
      "name": "せら",
      "age": 21,
      "height": 0,
      "bust": 0,
      "cup": "",
      "waist": 0,
      "hip": 0,
      "description": ""
    },
    {
      "id": "1071-2",
      "name": "のえる",
      "age": 20,
      "height": 0,
      "bust": 0,
      "cup": "",
      "waist": 0,
      "hip": 0,
      "description": ""
    },
    {
      "id": "1071-3",
      "name": "ゆめか",
      "age": 20,
      "height": 0,
      "bust": 0,
      "cup": "",
      "waist": 0,
      "hip": 0,
      "description": ""
    },
    {
      "id": "1071-4",
      "name": "みゆう",
      "age": 20,
      "height": 0,
      "bust": 0,
      "cup": "",
      "waist": 0,
      "hip": 0,
      "description": ""
    },
    {
      "id": "1071-5",
      "name": "らむ",
      "age": 20,
      "height": 0,
      "bust": 0,
      "cup": "",
      "waist": 0,
      "hip": 0,
      "description": ""
    },
    {
      "id": "1071-6",
      "name": "あいす",
      "age": 21,
      "height": 0,
      "bust": 0,
      "cup": "",
      "waist": 0,
      "hip": 0,
      "description": ""
    },
    {
      "id": "1071-7",
      "name": "らな",
      "age": 20,
      "height": 0,
      "bust": 0,
      "cup": "",
      "waist": 0,
      "hip": 0,
      "description": ""
    },
    {
      "id": "1071-8",
      "name": "あやか",
      "age": 23,
      "height": 0,
      "bust": 0,
      "cup": "",
      "waist": 0,
      "hip": 0,
      "description": ""
    },
    {
      "id": "1071-9",
      "name": "えな",
      "age": 20,
      "height": 0,
      "bust": 0,
      "cup": "",
      "waist": 0,
      "hip": 0,
      "description": ""
    },
    {
      "id": "1071-10",
      "name": "えま",
      "age": 23,
      "height": 0,
      "bust": 0,
      "cup": "",
      "waist": 0,
      "hip": 0,
      "description": ""
    },
    {
      "id": "1071-11",
      "name": "さき",
      "age": 19,
      "height": 0,
      "bust": 0,
      "cup": "",
      "waist": 0,
      "hip": 0,
      "description": ""
    },
    {
      "id": "1071-12",
      "name": "すい",
      "age": 19,
      "height": 0,
      "bust": 0,
      "cup": "",
      "waist": 0,
      "hip": 0,
      "description": ""
    },
    {
      "id": "1071-13",
      "name": "りり",
      "age": 22,
      "height": 0,
      "bust": 0,
      "cup": "",
      "waist": 0,
      "hip": 0,
      "description": ""
    },
    {
      "id": "1071-14",
      "name": "つむぎ",
      "age": 20,
      "height": 0,
      "bust": 0,
      "cup": "",
      "waist": 0,
      "hip": 0,
      "description": ""
    },
    {
      "id": "1071-15",
      "name": "るか",
      "age": 21,
      "height": 0,
      "bust": 0,
      "cup": "",
      "waist": 0,
      "hip": 0,
      "description": ""
    },
    {
      "id": "1071-16",
      "name": "りか",
      "age": 22,
      "height": 0,
      "bust": 0,
      "cup": "",
      "waist": 0,
      "hip": 0,
      "description": ""
    },
    {
      "id": "1071-17",
      "name": "うさ",
      "age": 22,
      "height": 0,
      "bust": 0,
      "cup": "",
      "waist": 0,
      "hip": 0,
      "description": ""
    },
    {
      "id": "1071-18",
      "name": "ゆの",
      "age": 24,
      "height": 0,
      "bust": 0,
      "cup": "",
      "waist": 0,
      "hip": 0,
      "description": ""
    },
    {
      "id": "1071-19",
      "name": "れん",
      "age": 20,
      "height": 0,
      "bust": 0,
      "cup": "",
      "waist": 0,
      "hip": 0,
      "description": ""
    },
    {
      "id": "1071-20",
      "name": "さな",
      "age": 22,
      "height": 0,
      "bust": 0,
      "cup": "",
      "waist": 0,
      "hip": 0,
      "description": ""
    },
    {
      "id": "1071-21",
      "name": "ゆき",
      "age": 20,
      "height": 0,
      "bust": 0,
      "cup": "",
      "waist": 0,
      "hip": 0,
      "description": ""
    },
    {
      "id": "1071-22",
      "name": "りあ",
      "age": 19,
      "height": 0,
      "bust": 0,
      "cup": "",
      "waist": 0,
      "hip": 0,
      "description": ""
    },
    {
      "id": "1071-23",
      "name": "ゆゆ",
      "age": 23,
      "height": 0,
      "bust": 0,
      "cup": "",
      "waist": 0,
      "hip": 0,
      "description": ""
    },
    {
      "id": "1071-24",
      "name": "らら",
      "age": 23,
      "height": 0,
      "bust": 0,
      "cup": "",
      "waist": 0,
      "hip": 0,
      "description": ""
    },
    {
      "id": "1071-25",
      "name": "さら",
      "age": 25,
      "height": 0,
      "bust": 0,
      "cup": "",
      "waist": 0,
      "hip": 0,
      "description": ""
    },
    {
      "id": "1071-26",
      "name": "りこ",
      "age": 19,
      "height": 0,
      "bust": 0,
      "cup": "",
      "waist": 0,
      "hip": 0,
      "description": ""
    },
    {
      "id": "1071-27",
      "name": "しほ",
      "age": 21,
      "height": 0,
      "bust": 0,
      "cup": "",
      "waist": 0,
      "hip": 0,
      "description": ""
    },
    {
      "id": "1071-28",
      "name": "ゆら",
      "age": 23,
      "height": 0,
      "bust": 0,
      "cup": "",
      "waist": 0,
      "hip": 0,
      "description": ""
    },
    {
      "id": "1071-29",
      "name": "あんな",
      "age": 23,
      "height": 0,
      "bust": 0,
      "cup": "",
      "waist": 0,
      "hip": 0,
      "description": ""
    },
    {
      "id": "1071-30",
      "name": "みあ",
      "age": 21,
      "height": 0,
      "bust": 0,
      "cup": "",
      "waist": 0,
      "hip": 0,
      "description": ""
    },
    {
      "id": "1071-31",
      "name": "きり",
      "age": 22,
      "height": 0,
      "bust": 0,
      "cup": "",
      "waist": 0,
      "hip": 0,
      "description": ""
    },
    {
      "id": "1071-32",
      "name": "りん",
      "age": 21,
      "height": 0,
      "bust": 0,
      "cup": "",
      "waist": 0,
      "hip": 0,
      "description": ""
    },
    {
      "id": "1071-33",
      "name": "すず",
      "age": 20,
      "height": 0,
      "bust": 0,
      "cup": "",
      "waist": 0,
      "hip": 0,
      "description": ""
    },
    {
      "id": "1071-34",
      "name": "きらら",
      "age": 19,
      "height": 0,
      "bust": 0,
      "cup": "",
      "waist": 0,
      "hip": 0,
      "description": ""
    },
    {
      "id": "1071-35",
      "name": "みなみ",
      "age": 23,
      "height": 0,
      "bust": 0,
      "cup": "",
      "waist": 0,
      "hip": 0,
      "description": ""
    },
    {
      "id": "1071-36",
      "name": "みつき",
      "age": 20,
      "height": 0,
      "bust": 0,
      "cup": "",
      "waist": 0,
      "hip": 0,
      "description": ""
    },
    {
      "id": "1071-37",
      "name": "かんな",
      "age": 21,
      "height": 0,
      "bust": 0,
      "cup": "",
      "waist": 0,
      "hip": 0,
      "description": ""
    },
    {
      "id": "1071-38",
      "name": "みき",
      "age": 20,
      "height": 0,
      "bust": 0,
      "cup": "",
      "waist": 0,
      "hip": 0,
      "description": ""
    },
    {
      "id": "1071-39",
      "name": "るあ",
      "age": 19,
      "height": 0,
      "bust": 0,
      "cup": "",
      "waist": 0,
      "hip": 0,
      "description": ""
    },
    {
      "id": "1071-40",
      "name": "みお",
      "age": 23,
      "height": 0,
      "bust": 0,
      "cup": "",
      "waist": 0,
      "hip": 0,
      "description": ""
    },
    {
      "id": "1071-41",
      "name": "ここなっつ",
      "age": 22,
      "height": 0,
      "bust": 0,
      "cup": "",
      "waist": 0,
      "hip": 0,
      "description": ""
    },
    {
      "id": "1071-42",
      "name": "せいな",
      "age": 20,
      "height": 0,
      "bust": 0,
      "cup": "",
      "waist": 0,
      "hip": 0,
      "description": ""
    },
    {
      "id": "1071-43",
      "name": "かすみ",
      "age": 19,
      "height": 0,
      "bust": 0,
      "cup": "",
      "waist": 0,
      "hip": 0,
      "description": ""
    },
    {
      "id": "1071-44",
      "name": "おと",
      "age": 24,
      "height": 0,
      "bust": 0,
      "cup": "",
      "waist": 0,
      "hip": 0,
      "description": ""
    },
    {
      "id": "1071-45",
      "name": "るな",
      "age": 20,
      "height": 0,
      "bust": 0,
      "cup": "",
      "waist": 0,
      "hip": 0,
      "description": ""
    },
    {
      "id": "1071-46",
      "name": "まりあ",
      "age": 19,
      "height": 0,
      "bust": 0,
      "cup": "",
      "waist": 0,
      "hip": 0,
      "description": ""
    },
    {
      "id": "1071-47",
      "name": "いろは",
      "age": 19,
      "height": 0,
      "bust": 0,
      "cup": "",
      "waist": 0,
      "hip": 0,
      "description": ""
    },
    {
      "id": "1071-48",
      "name": "れな",
      "age": 23,
      "height": 0,
      "bust": 0,
      "cup": "",
      "waist": 0,
      "hip": 0,
      "description": "可愛い系 / キレカワ系 / 清楚系 / 癒し系"
    },
    {
      "id": "1071-49",
      "name": "ひな",
      "age": 21,
      "height": 0,
      "bust": 0,
      "cup": "",
      "waist": 0,
      "hip": 0,
      "description": ""
    },
    {
      "id": "1071-50",
      "name": "もな",
      "age": 22,
      "height": 0,
      "bust": 0,
      "cup": "",
      "waist": 0,
      "hip": 0,
      "description": ""
    },
    {
      "id": "1071-51",
      "name": "かれん",
      "age": 23,
      "height": 0,
      "bust": 0,
      "cup": "",
      "waist": 0,
      "hip": 0,
      "description": ""
    },
    {
      "id": "1071-52",
      "name": "はるな",
      "age": 21,
      "height": 0,
      "bust": 0,
      "cup": "",
      "waist": 0,
      "hip": 0,
      "description": ""
    },
    {
      "id": "1071-53",
      "name": "あんり",
      "age": 20,
      "height": 0,
      "bust": 0,
      "cup": "",
      "waist": 0,
      "hip": 0,
      "description": "可愛い系 / 愛嬌◎ / スレンダー / 人懐っこい"
    },
    {
      "id": "1071-54",
      "name": "かりん",
      "age": 23,
      "height": 0,
      "bust": 0,
      "cup": "",
      "waist": 0,
      "hip": 0,
      "description": ""
    },
    {
      "id": "1071-55",
      "name": "さくら",
      "age": 21,
      "height": 0,
      "bust": 0,
      "cup": "",
      "waist": 0,
      "hip": 0,
      "description": ""
    },
    {
      "id": "1071-56",
      "name": "なな",
      "age": 21,
      "height": 0,
      "bust": 0,
      "cup": "",
      "waist": 0,
      "hip": 0,
      "description": ""
    },
    {
      "id": "1071-57",
      "name": "きてぃ",
      "age": 0,
      "height": 0,
      "bust": 0,
      "cup": "",
      "waist": 0,
      "hip": 0,
      "description": "かわいい系 / 愛嬌◎ / スレンダー / 人懐っこい"
    },
    {
      "id": "1071-58",
      "name": "せいら",
      "age": 23,
      "height": 0,
      "bust": 0,
      "cup": "",
      "waist": 0,
      "hip": 0,
      "description": ""
    },
    {
      "id": "1071-59",
      "name": "ななし",
      "age": 19,
      "height": 0,
      "bust": 0,
      "cup": "",
      "waist": 0,
      "hip": 0,
      "description": ""
    },
    {
      "id": "1071-60",
      "name": "おゆ",
      "age": 21,
      "height": 0,
      "bust": 0,
      "cup": "",
      "waist": 0,
      "hip": 0,
      "description": ""
    },
    {
      "id": "1071-61",
      "name": "よる",
      "age": 19,
      "height": 0,
      "bust": 0,
      "cup": "",
      "waist": 0,
      "hip": 0,
      "description": ""
    },
    {
      "id": "1071-62",
      "name": "りぜ",
      "age": 24,
      "height": 0,
      "bust": 0,
      "cup": "",
      "waist": 0,
      "hip": 0,
      "description": ""
    },
    {
      "id": "1071-63",
      "name": "なぎさ",
      "age": 21,
      "height": 0,
      "bust": 0,
      "cup": "",
      "waist": 0,
      "hip": 0,
      "description": ""
    },
    {
      "id": "1071-64",
      "name": "もも",
      "age": 24,
      "height": 0,
      "bust": 0,
      "cup": "",
      "waist": 0,
      "hip": 0,
      "description": ""
    },
    {
      "id": "1071-65",
      "name": "ゆめ",
      "age": 21,
      "height": 0,
      "bust": 0,
      "cup": "",
      "waist": 0,
      "hip": 0,
      "description": ""
    },
    {
      "id": "1071-66",
      "name": "まりな",
      "age": 22,
      "height": 0,
      "bust": 0,
      "cup": "",
      "waist": 0,
      "hip": 0,
      "description": ""
    },
    {
      "id": "1071-67",
      "name": "つきは",
      "age": 19,
      "height": 0,
      "bust": 0,
      "cup": "",
      "waist": 0,
      "hip": 0,
      "description": "可愛い系 / スタイル抜群 / 愛嬌抜群 / 人懐っこい"
    },
    {
      "id": "1071-68",
      "name": "ゆい",
      "age": 23,
      "height": 0,
      "bust": 0,
      "cup": "",
      "waist": 0,
      "hip": 0,
      "description": ""
    },
    {
      "id": "1071-69",
      "name": "ゆん",
      "age": 20,
      "height": 0,
      "bust": 0,
      "cup": "",
      "waist": 0,
      "hip": 0,
      "description": "可愛い系 / 愛嬌抜群 / 人懐っこい / スレンダー"
    },
    {
      "id": "1071-70",
      "name": "まな",
      "age": 22,
      "height": 0,
      "bust": 0,
      "cup": "",
      "waist": 0,
      "hip": 0,
      "description": "可愛い系 / 癒し系 / 清楚系 / 愛嬌抜群"
    },
    {
      "id": "1071-71",
      "name": "みさき",
      "age": 20,
      "height": 0,
      "bust": 0,
      "cup": "",
      "waist": 0,
      "hip": 0,
      "description": ""
    },
    {
      "id": "1071-72",
      "name": "みれい",
      "age": 21,
      "height": 0,
      "bust": 0,
      "cup": "",
      "waist": 0,
      "hip": 0,
      "description": ""
    },
    {
      "id": "1071-73",
      "name": "ありさ",
      "age": 21,
      "height": 0,
      "bust": 0,
      "cup": "",
      "waist": 0,
      "hip": 0,
      "description": ""
    },
    {
      "id": "1071-74",
      "name": "ねね",
      "age": 21,
      "height": 0,
      "bust": 0,
      "cup": "",
      "waist": 0,
      "hip": 0,
      "description": "可愛い系 / 巨乳 / 人懐っこい / 癒し系"
    },
    {
      "id": "1071-75",
      "name": "きら",
      "age": 22,
      "height": 0,
      "bust": 0,
      "cup": "",
      "waist": 0,
      "hip": 0,
      "description": ""
    },
    {
      "id": "1071-76",
      "name": "ゆな",
      "age": 19,
      "height": 0,
      "bust": 0,
      "cup": "",
      "waist": 0,
      "hip": 0,
      "description": ""
    },
    {
      "id": "1071-77",
      "name": "いと",
      "age": 21,
      "height": 0,
      "bust": 0,
      "cup": "",
      "waist": 0,
      "hip": 0,
      "description": ""
    },
    {
      "id": "1071-78",
      "name": "らいむ",
      "age": 19,
      "height": 0,
      "bust": 0,
      "cup": "",
      "waist": 0,
      "hip": 0,
      "description": ""
    },
    {
      "id": "1071-79",
      "name": "とうか",
      "age": 20,
      "height": 0,
      "bust": 0,
      "cup": "",
      "waist": 0,
      "hip": 0,
      "description": ""
    },
    {
      "id": "1071-80",
      "name": "そら",
      "age": 25,
      "height": 0,
      "bust": 0,
      "cup": "",
      "waist": 0,
      "hip": 0,
      "description": "可愛い系 / 巨乳 / 清楚系 / お姉さん系"
    }
  ],
  "brandId": "aroma_one"
}