{
  "id": 1155,
  "name": "LIVSPA (リブスパ)",
  "prefecture": "神奈川県",
  "city": "川崎",
  "area": "川崎",
  "address": "東京都大田区・目黒区／神奈川県川崎市",
  "image": "/images/shops/no_image.jpg",
  "rating": 0,
  "reviewCount": 0,
  "price": "90分 18,000円～",
  "hours": "10:00～翌5:00",
  "isPremium": false,
  "tags": [
    "完全個室",
    "深夜営業"
  ],
  "websiteUrl": "https://livspa.net/",
  "nearestStation": "蒲田駅/川崎駅/自由が丘駅",
  "description": "蒲田・川崎・自由が丘のメンズエステ。90分18,000円から。",
  "therapists": [
    {
      "id": "1155-1",
      "name": "深澤まき",
      "age": 24,
      "height": 158,
      "bust": 0,
      "cup": "H",
      "waist": 0,
      "hip": 0,
      "description": ""
    },
    {
      "id": "1155-2",
      "name": "水瀬もも",
      "age": 23,
      "height": 162,
      "bust": 0,
      "cup": "G",
      "waist": 0,
      "hip": 0,
      "description": ""
    },
    {
      "id": "1155-3",
      "name": "みかげなぎ",
      "age": 26,
      "height": 168,
      "bust": 0,
      "cup": "D",
      "waist": 0,
      "hip": 0,
      "description": "新人 現役RQ極液認定セラピスト"
    },
    {
      "id": "1155-4",
      "name": "ゆいかことは",
      "age": 24,
      "height": 158,
      "bust": 0,
      "cup": "C",
      "waist": 0,
      "hip": 0,
      "description": "新人 現役看護師セラピスト"
    },
    {
      "id": "1155-5",
      "name": "いちのせあいり",
      "age": 21,
      "height": 155,
      "bust": 0,
      "cup": "F",
      "waist": 0,
      "hip": 0,
      "description": "新人 現役JD"
    },
    {
      "id": "1155-6",
      "name": "かすみがおかさくら",
      "age": 23,
      "height": 153,
      "bust": 0,
      "cup": "E",
      "waist": 0,
      "hip": 0,
      "description": "新人 可憐"
    },
    {
      "id": "1155-7",
      "name": "あやせみあ",
      "age": 23,
      "height": 161,
      "bust": 0,
      "cup": "E",
      "waist": 0,
      "hip": 0,
      "description": "新人"
    },
    {
      "id": "1155-8",
      "name": "かんだえりか",
      "age": 22,
      "height": 163,
      "bust": 0,
      "cup": "E",
      "waist": 0,
      "hip": 0,
      "description": "新人 Kpop系セラピスト"
    },
    {
      "id": "1155-9",
      "name": "天野かのん",
      "age": 20,
      "height": 157,
      "bust": 0,
      "cup": "F",
      "waist": 0,
      "hip": 0,
      "description": "看護師セラピスト"
    },
    {
      "id": "1155-10",
      "name": "高橋まりな",
      "age": 22,
      "height": 153,
      "bust": 0,
      "cup": "D",
      "waist": 0,
      "hip": 0,
      "description": ""
    },
    {
      "id": "1155-11",
      "name": "工藤かなみ",
      "age": 25,
      "height": 160,
      "bust": 0,
      "cup": "E",
      "waist": 0,
      "hip": 0,
      "description": ""
    },
    {
      "id": "1155-12",
      "name": "月永らん",
      "age": 22,
      "height": 156,
      "bust": 0,
      "cup": "D",
      "waist": 0,
      "hip": 0,
      "description": ""
    },
    {
      "id": "1155-13",
      "name": "桃井あかり",
      "age": 22,
      "height": 157,
      "bust": 0,
      "cup": "E",
      "waist": 0,
      "hip": 0,
      "description": ""
    },
    {
      "id": "1155-14",
      "name": "成瀬ゆあ",
      "age": 21,
      "height": 168,
      "bust": 0,
      "cup": "F",
      "waist": 0,
      "hip": 0,
      "description": "元保育士セラピスト"
    },
    {
      "id": "1155-15",
      "name": "渚みお",
      "age": 23,
      "height": 160,
      "bust": 0,
      "cup": "E",
      "waist": 0,
      "hip": 0,
      "description": ""
    },
    {
      "id": "1155-16",
      "name": "柚月すずな",
      "age": 23,
      "height": 157,
      "bust": 0,
      "cup": "D",
      "waist": 0,
      "hip": 0,
      "description": ""
    },
    {
      "id": "1155-17",
      "name": "双葉なな",
      "age": 23,
      "height": 153,
      "bust": 0,
      "cup": "C",
      "waist": 0,
      "hip": 0,
      "description": "癒し系セラピスト"
    },
    {
      "id": "1155-18",
      "name": "空条りん",
      "age": 28,
      "height": 155,
      "bust": 0,
      "cup": "G",
      "waist": 0,
      "hip": 0,
      "description": ""
    },
    {
      "id": "1155-19",
      "name": "赤西めい",
      "age": 24,
      "height": 164,
      "bust": 0,
      "cup": "D",
      "waist": 0,
      "hip": 0,
      "description": ""
    },
    {
      "id": "1155-20",
      "name": "小野たまき",
      "age": 27,
      "height": 170,
      "bust": 0,
      "cup": "C",
      "waist": 0,
      "hip": 0,
      "description": ""
    },
    {
      "id": "1155-21",
      "name": "櫻井みづき",
      "age": 24,
      "height": 158,
      "bust": 0,
      "cup": "C",
      "waist": 0,
      "hip": 0,
      "description": ""
    },
    {
      "id": "1155-22",
      "name": "長峰らむ",
      "age": 24,
      "height": 151,
      "bust": 0,
      "cup": "G",
      "waist": 0,
      "hip": 0,
      "description": "元アイドルセラピスト"
    },
    {
      "id": "1155-23",
      "name": "上村れな",
      "age": 23,
      "height": 156,
      "bust": 0,
      "cup": "C",
      "waist": 0,
      "hip": 0,
      "description": ""
    },
    {
      "id": "1155-24",
      "name": "栗山あみ",
      "age": 22,
      "height": 152,
      "bust": 0,
      "cup": "D",
      "waist": 0,
      "hip": 0,
      "description": ""
    },
    {
      "id": "1155-25",
      "name": "萌木なの",
      "age": 22,
      "height": 160,
      "bust": 0,
      "cup": "F",
      "waist": 0,
      "hip": 0,
      "description": ""
    },
    {
      "id": "1155-26",
      "name": "癒川にな",
      "age": 25,
      "height": 150,
      "bust": 0,
      "cup": "C",
      "waist": 0,
      "hip": 0,
      "description": ""
    },
    {
      "id": "1155-27",
      "name": "藤田りこ",
      "age": 25,
      "height": 160,
      "bust": 0,
      "cup": "D",
      "waist": 0,
      "hip": 0,
      "description": "新人 《新人》体入"
    }
  ],
  "brandId": "livspa"
}