{
  "id": "tokyo_dispatch_aqua_premium",
  "name": "AQUA PREMIUM (アクアプレミアム)",
  "prefecture": "東京都",
  "city": "23区出張",
  "area": "23wards",
  "address": "東京都23区内出張",
  "image": "/images/shops/no_image.jpg",
  "rating": 0,
  "reviewCount": 0,
  "price": "60分 15,000円～",
  "hours": "12:00～翌5:00",
  "isPremium": false,
  "tags": [
    "23区出張",
    "派遣型",
    "深夜営業"
  ],
  "websiteUrl": "https://aqua-premium.com/",
  "nearestStation": "23区内出張",
  "description": "23区出張のメンズエステ。 / 料金システム: 60分15,000円 / 90分20,000円 / 120分25,000円 / 150分30,000円 / 180分35,000円",
  "brandId": "aqua_premium",
  "threads": [],
  "therapists": [
    "aqua_premium_石森れみ",
    "aqua_premium_松嶋ゆな",
    "aqua_premium_前田るい",
    "aqua_premium_倉木はるか",
    "aqua_premium_大野まみ",
    "aqua_premium_高城さえ",
    "aqua_premium_来栖ななこ",
    "aqua_premium_黒木あみ",
    "aqua_premium_住谷ゆい",
    "aqua_premium_美咲れん",
    "aqua_premium_楠木あやか",
    "aqua_premium_三上ゆうな",
    "aqua_premium_星川みひろ",
    "aqua_premium_矢沢あかね",
    "aqua_premium_深澤はるな",
    "aqua_premium_笹木まり",
    "aqua_premium_青羽れお",
    "aqua_premium_工藤なみ",
    "aqua_premium_村瀬かな",
    "aqua_premium_小森さき",
    "aqua_premium_城田みれい",
    "aqua_premium_春野るか",
    "aqua_premium_星野りあ",
    "aqua_premium_来栖きょうか",
    "aqua_premium_浅倉るい",
    "aqua_premium_咲良みおん",
    "aqua_premium_天音もも",
    "aqua_premium_南つばさ",
    "aqua_premium_白咲ねね",
    "aqua_premium_夢宮せな",
    "aqua_premium_鈴村まいこ",
    "aqua_premium_叶まいか",
    "aqua_premium_花宮しずく",
    "aqua_premium_櫻井ななせ",
    "aqua_premium_今井もえか",
    "aqua_premium_愛沢ゆりあ",
    "aqua_premium_柊まゆか",
    "aqua_premium_梨本めい",
    "aqua_premium_望月ひなた",
    "aqua_premium_成沢みかな",
    "aqua_premium_美月まいか",
    "aqua_premium_桃源あゆり",
    "aqua_premium_上条ひなの",
    "aqua_premium_石垣あい",
    "aqua_premium_北このは",
    "aqua_premium_澤藤みき",
    "aqua_premium_満島めい",
    "aqua_premium_奥山いちか",
    "aqua_premium_吉永まゆ",
    "aqua_premium_香月りさ",
    "aqua_premium_小池みこ",
    "aqua_premium_桜庭ひな",
    "aqua_premium_涼森さな",
    "aqua_premium_夏樹ゆいか",
    "aqua_premium_葉月とうか",
    "aqua_premium_桃瀬みづき",
    "aqua_premium_及川ゆみ",
    "aqua_premium_柚木まな",
    "aqua_premium_雪城はるな",
    "aqua_premium_柴咲まりか",
    "aqua_premium_音田みゆ",
    "aqua_premium_瀬乃ゆりか",
    "aqua_premium_望月まりあ",
    "aqua_premium_橋本さな",
    "aqua_premium_麻実れお",
    "aqua_premium_森下ゆう",
    "aqua_premium_村上かなえ",
    "aqua_premium_鶴城ななえ",
    "aqua_premium_橘ゆいな",
    "aqua_premium_永田もも",
    "aqua_premium_観月れいな",
    "aqua_premium_葵ひな",
    "aqua_premium_福原あいみ",
    "aqua_premium_木村あかり",
    "aqua_premium_岡崎みゆ",
    "aqua_premium_奥田りさこ",
    "aqua_premium_坂間なゆ",
    "aqua_premium_長澤ありな",
    "aqua_premium_白鳥こはる",
    "aqua_premium_香川なつき",
    "aqua_premium_水谷りか",
    "aqua_premium_浅野りほ",
    "aqua_premium_瀬戸内えま",
    "aqua_premium_久遠みかこ",
    "aqua_premium_羽澤ゆき",
    "aqua_premium_吉瀬すずな",
    "aqua_premium_風吹りつ",
    "aqua_premium_姫川あんり",
    "aqua_premium_篠宮まりあ",
    "aqua_premium_仁科かえで",
    "aqua_premium_仁木れいか",
    "aqua_premium_染谷あやみ",
    "aqua_premium_三花えれな",
    "aqua_premium_寿いろは",
    "aqua_premium_君島りこ",
    "aqua_premium_紺野ゆい",
    "aqua_premium_一ノ瀬こゆき",
    "aqua_premium_葉山ゆりの",
    "aqua_premium_夢咲りりか",
    "aqua_premium_天野うら",
    "aqua_premium_竹内りさ",
    "aqua_premium_藤井なな",
    "aqua_premium_高橋ありさ",
    "aqua_premium_山崎みお"
  ]
}