{
  "id": 1181,
  "name": "美吟 (ビギン) 船橋店",
  "prefecture": "千葉県",
  "city": "西船橋",
  "area": "西船橋",
  "address": "千葉県船橋市",
  "image": "/images/shops/no_image.jpg",
  "rating": 0,
  "reviewCount": 0,
  "price": "60分 14,000円～",
  "hours": "10:00～翌1:00",
  "isPremium": false,
  "tags": [
    "完全個室"
  ],
  "websiteUrl": "https://aroma-bigin.net/",
  "nearestStation": "船橋駅/西船橋駅",
  "description": "船橋・西船橋のメンズエステ。60分14,000円から。",
  "therapists": [
    {
      "id": "1181-1",
      "name": "池田",
      "age": 30,
      "height": 160,
      "bust": 89,
      "cup": "",
      "waist": 58,
      "hip": 87,
      "description": ""
    },
    {
      "id": "1181-2",
      "name": "七海",
      "age": 31,
      "height": 158,
      "bust": 89,
      "cup": "",
      "waist": 59,
      "hip": 89,
      "description": ""
    },
    {
      "id": "1181-3",
      "name": "黒崎",
      "age": 31,
      "height": 161,
      "bust": 91,
      "cup": "",
      "waist": 59,
      "hip": 89,
      "description": ""
    },
    {
      "id": "1181-4",
      "name": "本宮",
      "age": 40,
      "height": 160,
      "bust": 88,
      "cup": "",
      "waist": 59,
      "hip": 87,
      "description": ""
    },
    {
      "id": "1181-5",
      "name": "藤原",
      "age": 34,
      "height": 159,
      "bust": 86,
      "cup": "",
      "waist": 56,
      "hip": 85,
      "description": ""
    },
    {
      "id": "1181-6",
      "name": "持月",
      "age": 37,
      "height": 171,
      "bust": 87,
      "cup": "",
      "waist": 58,
      "hip": 86,
      "description": ""
    },
    {
      "id": "1181-7",
      "name": "浅井",
      "age": 40,
      "height": 153,
      "bust": 84,
      "cup": "",
      "waist": 56,
      "hip": 83,
      "description": ""
    },
    {
      "id": "1181-8",
      "name": "安室",
      "age": 33,
      "height": 152,
      "bust": 86,
      "cup": "",
      "waist": 58,
      "hip": 85,
      "description": ""
    },
    {
      "id": "1181-9",
      "name": "八木",
      "age": 31,
      "height": 159,
      "bust": 89,
      "cup": "",
      "waist": 58,
      "hip": 87,
      "description": ""
    },
    {
      "id": "1181-10",
      "name": "姫野",
      "age": 38,
      "height": 153,
      "bust": 88,
      "cup": "",
      "waist": 57,
      "hip": 86,
      "description": ""
    },
    {
      "id": "1181-11",
      "name": "倉田",
      "age": 41,
      "height": 152,
      "bust": 87,
      "cup": "",
      "waist": 56,
      "hip": 85,
      "description": ""
    },
    {
      "id": "1181-12",
      "name": "結城",
      "age": 30,
      "height": 153,
      "bust": 85,
      "cup": "",
      "waist": 57,
      "hip": 86,
      "description": ""
    },
    {
      "id": "1181-13",
      "name": "若槻",
      "age": 39,
      "height": 151,
      "bust": 87,
      "cup": "",
      "waist": 56,
      "hip": 84,
      "description": ""
    },
    {
      "id": "1181-14",
      "name": "七瀬",
      "age": 38,
      "height": 154,
      "bust": 87,
      "cup": "",
      "waist": 57,
      "hip": 86,
      "description": ""
    },
    {
      "id": "1181-15",
      "name": "木村",
      "age": 38,
      "height": 153,
      "bust": 86,
      "cup": "",
      "waist": 56,
      "hip": 84,
      "description": ""
    },
    {
      "id": "1181-16",
      "name": "坂口",
      "age": 38,
      "height": 157,
      "bust": 88,
      "cup": "",
      "waist": 57,
      "hip": 86,
      "description": ""
    },
    {
      "id": "1181-17",
      "name": "飯島",
      "age": 39,
      "height": 151,
      "bust": 85,
      "cup": "",
      "waist": 56,
      "hip": 84,
      "description": ""
    },
    {
      "id": "1181-18",
      "name": "綾瀬",
      "age": 30,
      "height": 160,
      "bust": 86,
      "cup": "",
      "waist": 56,
      "hip": 84,
      "description": ""
    },
    {
      "id": "1181-19",
      "name": "筒井",
      "age": 28,
      "height": 149,
      "bust": 88,
      "cup": "",
      "waist": 57,
      "hip": 86,
      "description": ""
    },
    {
      "id": "1181-20",
      "name": "柚月",
      "age": 32,
      "height": 159,
      "bust": 87,
      "cup": "",
      "waist": 57,
      "hip": 86,
      "description": ""
    },
    {
      "id": "1181-21",
      "name": "栗原",
      "age": 35,
      "height": 158,
      "bust": 87,
      "cup": "",
      "waist": 57,
      "hip": 86,
      "description": ""
    },
    {
      "id": "1181-22",
      "name": "椿",
      "age": 37,
      "height": 160,
      "bust": 87,
      "cup": "",
      "waist": 56,
      "hip": 86,
      "description": ""
    },
    {
      "id": "1181-23",
      "name": "菅野",
      "age": 36,
      "height": 165,
      "bust": 88,
      "cup": "",
      "waist": 56,
      "hip": 85,
      "description": ""
    },
    {
      "id": "1181-24",
      "name": "相川",
      "age": 39,
      "height": 152,
      "bust": 87,
      "cup": "",
      "waist": 57,
      "hip": 85,
      "description": ""
    },
    {
      "id": "1181-25",
      "name": "柴崎",
      "age": 32,
      "height": 160,
      "bust": 87,
      "cup": "",
      "waist": 56,
      "hip": 85,
      "description": ""
    },
    {
      "id": "1181-26",
      "name": "金城",
      "age": 31,
      "height": 165,
      "bust": 89,
      "cup": "",
      "waist": 58,
      "hip": 88,
      "description": ""
    },
    {
      "id": "1181-27",
      "name": "三上",
      "age": 38,
      "height": 154,
      "bust": 88,
      "cup": "",
      "waist": 57,
      "hip": 87,
      "description": ""
    },
    {
      "id": "1181-28",
      "name": "桃井",
      "age": 29,
      "height": 157,
      "bust": 86,
      "cup": "",
      "waist": 57,
      "hip": 84,
      "description": ""
    },
    {
      "id": "1181-29",
      "name": "天草",
      "age": 32,
      "height": 149,
      "bust": 90,
      "cup": "",
      "waist": 58,
      "hip": 88,
      "description": ""
    },
    {
      "id": "1181-30",
      "name": "西野",
      "age": 41,
      "height": 153,
      "bust": 83,
      "cup": "",
      "waist": 56,
      "hip": 84,
      "description": ""
    },
    {
      "id": "1181-31",
      "name": "君嶋",
      "age": 39,
      "height": 157,
      "bust": 86,
      "cup": "",
      "waist": 56,
      "hip": 86,
      "description": ""
    },
    {
      "id": "1181-32",
      "name": "大越",
      "age": 35,
      "height": 150,
      "bust": 84,
      "cup": "",
      "waist": 56,
      "hip": 83,
      "description": ""
    },
    {
      "id": "1181-33",
      "name": "双葉",
      "age": 31,
      "height": 155,
      "bust": 86,
      "cup": "",
      "waist": 56,
      "hip": 84,
      "description": ""
    },
    {
      "id": "1181-34",
      "name": "黒川",
      "age": 36,
      "height": 163,
      "bust": 88,
      "cup": "",
      "waist": 58,
      "hip": 87,
      "description": ""
    },
    {
      "id": "1181-35",
      "name": "椎名",
      "age": 33,
      "height": 147,
      "bust": 84,
      "cup": "",
      "waist": 55,
      "hip": 84,
      "description": ""
    },
    {
      "id": "1181-36",
      "name": "有村",
      "age": 39,
      "height": 155,
      "bust": 86,
      "cup": "",
      "waist": 56,
      "hip": 84,
      "description": ""
    },
    {
      "id": "1181-37",
      "name": "夢咲",
      "age": 45,
      "height": 156,
      "bust": 89,
      "cup": "",
      "waist": 59,
      "hip": 89,
      "description": ""
    }
  ],
  "brandId": "begin"
}